Metadata-Version: 2.1
Name: msd-model-regression-ligan
Version: 0.0.1
Summary: Example regression model package from Train In Data.
Home-page: https://github.com/LiganiumInc
Author: Liganium
Author-email: liganbernardin@gmail.com
License: BSD-3
Classifier: License :: OSI Approved :: MIT License
Classifier: Programming Language :: Python
Classifier: Programming Language :: Python :: 3
Classifier: Programming Language :: Python :: 3.6
Classifier: Programming Language :: Python :: 3.7
Classifier: Programming Language :: Python :: 3.8
Classifier: Programming Language :: Python :: 3.9
Classifier: Programming Language :: Python :: Implementation :: CPython
Classifier: Programming Language :: Python :: Implementation :: PyPy
Requires-Python: >=3.6.0
Requires-Dist: numpy
Requires-Dist: pandas
Requires-Dist: pydantic
Requires-Dist: scikit-learn
Requires-Dist: strictyaml
Requires-Dist: ruamel.yaml
Requires-Dist: feature-engine
Requires-Dist: joblib
